unifai/__init__.py
unifai/agent/__init__.py
unifai/agent/agent.py
unifai/agent/model.py
unifai/agent/utils.py
unifai/agent/prompts/agent.yaml
unifai/client/__init__.py
unifai/client/base.py
unifai/client/discord.py
unifai/client/telegram.py
unifai/client/twitter.py
unifai/common/__init__.py
unifai/common/api.py
unifai/common/const.py
unifai/memory/__init__.py
unifai/memory/base.py
unifai/memory/chroma.py
unifai/memory/exceptions.py
unifai/memory/plugin.py
unifai/memory/protocols.py
unifai/memory/tool_plugin.py
unifai/memory/utils.py
unifai/memory/examples/reflector_memory.py
unifai/reflector/__init__.py
unifai/reflector/base.py
unifai/reflector/fact.py
unifai/reflector/goal.py
unifai/reflector/types.py
unifai/toolkit/__init__.py
unifai/toolkit/api.py
unifai/toolkit/context.py
unifai/toolkit/messages.py
unifai/toolkit/toolkit.py
unifai/tools/__init__.py
unifai/tools/api.py
unifai/tools/tools.py
unifai/tools/mcp/__init__.py
unifai/tools/mcp/__main__.py
unifai/tools/mcp/server.py
unifai_sdk-0.3.3.dist-info/METADATA
unifai_sdk-0.3.3.dist-info/WHEEL
unifai_sdk-0.3.3.dist-info/entry_points.txt
unifai_sdk-0.3.3.dist-info/licenses/LICENSE
unifai_sdk-0.3.3.dist-info/RECORD
