Metadata-Version: 2.4
Name: unifai-sdk
Version: 0.3.3
Summary: UnifAI Python SDK
Project-URL: Homepage, https://github.com/unifai-network/unifai-sdk-py
Project-URL: Issues, https://github.com/unifai-network/unifai-sdk-py/issues
Author-email: UnifAI <contact@unifai.network>
License-Expression: MIT
License-File: LICENSE
Classifier: License :: OSI Approved :: MIT License
Classifier: Operating System :: OS Independent
Classifier: Programming Language :: Python :: 3
Requires-Python: >=3.10
Requires-Dist: aiofiles>=24.0.0
Requires-Dist: boto3>=1.37.3
Requires-Dist: chromadb>=0.6.0
Requires-Dist: discord-py>=2.5.2
Requires-Dist: google-cloud-aiplatform>=1.82.0
Requires-Dist: litellm>=1.63.0
Requires-Dist: mcp>=1.2.0
Requires-Dist: numpy>=2.0.0
Requires-Dist: pydantic>=2.0.0
Requires-Dist: python-telegram-bot>=20.0
Requires-Dist: pyyaml>=6.0
Requires-Dist: tenacity>=9.0.0
Requires-Dist: tweepy>=4.15.0
Requires-Dist: websockets>=10.0
